{
  "projects": [
    {
      "name": "projeto teste",
      "budget": "1000",
      "category": {
        "id": "4",
        "name": "Planejamento"
      },
      "cost": 0,
      "services": [],
      "id": 1
    },
    {
      "name": "JEAN LEAL DOS SANTOS",
      "budget": "13122",
      "category": {
        "id": "2",
        "name": "Desenvolvimento"
      }
    },
    {
      "name": "Projeto Novo",
      "budget": "500",
      "category": {
        "id": "3",
        "name": "Design"
      },
      "cost": 0,
      "services": [],
      "id": 2
    }
  ],
  "categories": [
    {
      "id": 1,
      "name": "Infra"
    },
    {
      "id": 2,
      "name": "Desenvolvimento"
    },
    {
      "id": 3,
      "name": "Design"
    },
    {
      "id": 4,
      "name": "Planejamento"
    }
  ]
}